pymailsac/__init__.py
pymailsac/client.py
pymailsac/schemas.py
pymailsac-0.1.4.dist-info/LICENSE
pymailsac-0.1.4.dist-info/METADATA
pymailsac-0.1.4.dist-info/WHEEL
pymailsac-0.1.4.dist-info/RECORD
