Metadata-Version: 2.1
Name: pymailsac
Version: 0.1.4
Summary: API Wrapper Client for Mailsac
Home-page: https://github.com/GSejas/mailsac-pyclient
License: MIT
Keywords: mailsac,api,wrapper,client
Author: GSejas
Author-email: jsequeira03@gmail.com
Requires-Python: >=3.9,<4.0
Classifier: License :: OSI Approved :: MIT License
Classifier: Operating System :: OS Independent
Classifier: Programming Language :: Python :: 3
Classifier: Programming Language :: Python :: 3.9
Classifier: Programming Language :: Python :: 3.10
Classifier: Programming Language :: Python :: 3.11
Classifier: Programming Language :: Python :: 3.12
Classifier: Programming Language :: Python :: 3.13
Requires-Dist: pydantic (>=2.9.2,<3.0.0)
Requires-Dist: requests (>=2.32.3,<3.0.0)
Project-URL: Documentation, https://github.com/GSejas/mailsac-pyclient/blob/master/README.md
Project-URL: Repository, https://github.com/GSejas/mailsac-pyclient
